MANIFEST.in
README.rst
setup.cfg
setup.py
bin/par2ls
bin/par2mv
bin/par2unrar
par2ools/__init__.py
par2ools/fileutil.py
par2ools/par2.py
par2ools.egg-info/PKG-INFO
par2ools.egg-info/SOURCES.txt
par2ools.egg-info/dependency_links.txt
par2ools.egg-info/entry_points.txt
par2ools.egg-info/not-zip-safe
par2ools.egg-info/top_level.txt