Metadata-Version: 1.1
Name: par2ools
Version: 0.1
Summary: par2 tools
Home-page: http://github.com/jmoiron/par2ools
Author: Jason Moiron
Author-email: jmoiron@jmoiron.net
License: MIT
Keywords: par2
Platform: UNKNOWN
Classifier: Development Status :: 4 - Beta
Classifier: License :: OSI Approved :: MIT License
